shrt/__init__.py
shrt/__main__.py
shrt/app.py
shrt/cli/__init__.py
shrt/cli/__main__.py
shrt/cli/base.py
shrt/cli/main.py
shrt/cli/url.py
shrt/database.py
shrt/schemas.py
shrt/settings.py
shrt/utils/__init__.py
shrt/utils/cache.py
shrt/utils/strings.py
shrt/views/__init__.py
shrt/views/redirect.py
shrt/views/status.py
shrt/web.py
shrt-0.3.0.dist-info/LICENSE
shrt-0.3.0.dist-info/METADATA
shrt-0.3.0.dist-info/WHEEL
shrt-0.3.0.dist-info/entry_points.txt
shrt-0.3.0.dist-info/RECORD
