Metadata-Version: 2.1
Name: shrt
Version: 0.3.0
Summary: Shorten URLs
Home-page: https://gitlab.com/uda/shrt
License: MIT
Author: Yehuda Deutsch
Author-email: yeh@uda.co.il
Maintainer: Yehuda Deutsch
Maintainer-email: yeh@uda.co.il
Requires-Python: >=3.10,<4.0
Classifier: License :: OSI Approved :: MIT License
Classifier: Programming Language :: Python :: 3
Classifier: Programming Language :: Python :: 3.10
Classifier: Programming Language :: Python :: 3.11
Provides-Extra: cache
Requires-Dist: SQLAlchemy (>=2.0.19,<3.0.0)
Requires-Dist: aiosqlite (>=0.19.0,<0.20.0)
Requires-Dist: asyncpg (>=0.28.0,<0.29.0)
Requires-Dist: fastapi-jinja (>=0.2.0,<0.3.0)
Requires-Dist: fastapi[all] (>=0.100.0,<0.101.0)
Requires-Dist: pydantic-settings (>=2.0.1,<3.0.0)
Requires-Dist: redis (>=4.6.0,<5.0.0) ; extra == "cache"
Requires-Dist: tabulate (>=0.9.0,<0.10.0)
Requires-Dist: typer[all] (>=0.9.0,<0.10.0)
Project-URL: Bug Tracker, https://gitlab.com/uda/shrt/-/issues
Project-URL: Repository, https://gitlab.com/uda/shrt
